{"number":530,"writer":"KVS","starts":"refrain","refrain":["എത്ര നല്ലോരിടയനെൻ യേശു നസറേശൻ!","നിത്യവുമെൻ മുട്ടുകളെ തീർത്തിടുന്നോരീശൻ!"],"verses":[{"number":1,"lines":["പച്ചമേച്ചിൽ സ്ഥലങ്ങളിൽ","ഞാൻ നടന്നു മേയും","ശാന്തമായ വെളളം കുടിച്ചാ’","നന്ദിച്ചു തുളളും -"]},{"number":2,"lines":["ആകുലമശേഷം നീക്കി","പ്രാണനെയെന്നാഥൻ","ആദരവായ് തണുപ്പിക്കു -","ന്നേശു നസറേശൻ"]},{"number":3,"lines":["നീതിപാതയറിഞ്ഞു","ഞാൻ സഞ്ചരിക്കുന്നിപ്പോൾ","ഭീതിയില്ല, കൂരിരുളിൻ","താഴ്‌വരയിൽ പോലും -"]},{"number":4,"lines":["തൻവടിയുംകോലുമെന്നെ -","യാശ്വസിപ്പിക്കുന്നു","ശത്രുവിൻ മുമ്പെനിക്കവൻ","മേശയൊരുക്കുന്നു"]},{"number":5,"lines":["എന്നുടെ തലയിലെണ്ണ","തിങ്ങിയൊഴുകുന്നു","ഞാൻ കുടിക്കും പാത്രമോ","നിറഞ്ഞു കവിയുന്നു"]},{"number":6,"lines":["നന്മയും കൃപയുമെന്നെ","തേടി വരുമെന്നും","ദൈവഭവനത്തിൽ വാഴും","ദീർഘകാലമീ ഞാൻ"]}]}