{"number":635,"writer":"MEC","starts":"refrain","refrain":["യഹോവ ദൈവമാം വിശുദ്ധ ജാതി നാം","അവനവകാശമാം ജനം നാം","പരദേശികൾ നാം ഭാഗ്യശാലികൾ","ഇതുപോലൊരു ജാതിയുണ്ടോ!"],"verses":[{"number":1,"lines":["ആപത്തിൽ നമ്മുടെ ദിവ്യസങ്കേതവും","ബലവും ദൈവം ഒരുവനത്രേ","ആകയാൽ പാരിടം ആകെയിളകിലും","നാമിനി ഭയപ്പെടുകയില്ല"]},{"number":2,"lines":["അവനീതലത്തിൽ അപമാനം","നമുക്കവകാശമെന്നോർത്തിടണം","അവന്നായ് കഷ്ടതയേൽക്കുകിൽ","തേജസ്സിൽ അനന്തയുഗം വാണിടും നാം"]},{"number":3,"lines":["നിര നിര നിരയായ് അണിനിരന്നിടുവിൻ","കുരിശിൻ പടയാളികളെ","ജയ ജയ ജയ കാഹളമൂതിടുവിൻ","ജയവീരനാം യേശുവിന്നു"]}]}