{"number":676,"writer":"KVI","starts":"verse-1","refrain":["നുകമണിഞ്ഞനുസരിച്ച -","വന്റെ പിൻപേ നാം","അവൻ പദം പഠിച്ചു","പാദം പിൻഗമിച്ചിടാം"],"verses":[{"number":1,"lines":["വരു വരു സഹജരെ","കുരിശെടുത്തു നാം","ഗുരുവരന്റെ പിൻപേ നാം","ഗമിച്ചിടാമിനി"]},{"number":2,"lines":["സൽപ്രബോധനത്തിനായി","ചെവിയുണർത്തിടാം","ക്ഷീണരെ ഉണർത്തുവാൻ","നാവൊരുക്കിടാം -"]},{"number":3,"lines":["അവനിയിൽ ലവണമായി","നാമിരിക്കയും","അവനുവേണ്ടി സാക്ഷിചൊല്ലി","നാൾ കഴിക്കയും -"]},{"number":4,"lines":["ഇക്ഷിതിയിൽ ദീപമായി","ജ്വലിച്ചിടാമിനി","കക്ഷിപക്ഷം ഇക്ഷണം","വെടിഞ്ഞിടാം അഹം -"]},{"number":5,"lines":["ഉയർന്നതാം മലയ്ക്കു","തുല്യരായിരിക്ക നാം","മറച്ചിടാതെ സത്യവേദം","ഓതിടാമിനി -"]},{"number":6,"lines":["കുരിശിലേറി ജീവനെ","കൊടുത്ത നാഥനെ","നിണമണിഞ്ഞ തൻ പാദങ്ങൾ","പിൻഗമിച്ചു നാം"]}]}