{"number":700,"writer":"PJA","starts":"verse-1","refrain":[],"verses":[{"number":1,"lines":["അനുദിനവും അരികിലുളള","അരുമനാഥൻ മതിയെനിക്ക്","അനവധിയായ് അനുഗ്രഹങ്ങൾ","അരുളിയെന്നെ അണയ്ക്കുമവൻ"]},{"number":2,"lines":["ഒരു നിമിഷം മറന്നിടാതെ","ഒരുദിനവും കൈവിടാതെ","തിരുചിറകിൽ മറവിലെന്നെ","ചേർത്തണയ്ക്കും നാഥനവൻ"]},{"number":3,"lines":["ഏറിവരും ആധികളിൽ","ഏകനല്ല പാരിതിൽ ഞാൻ","ഏവരും കൈവിട്ടെന്നാലും","ഏറ്റവും നൽ മിത്രമവൻ"]},{"number":4,"lines":["പാരിതിലെൻ പാതയിൽ ഞാൻ","പതറിടാതെ പരിപാലിക്കും","പരമനാഥൻ മറവിടമാം","പരമപദം അണയുവോളം"]}]}