{"number":788,"writer":"TMK","starts":"refrain","refrain":["ആകുലനായിതീരരുതേയെൻ മനമേ","യേശുനാഥൻ നീക്കിടും","നിന്റെ ക്ലേശമെല്ലാം"],"verses":[{"number":1,"lines":["പുലർത്തുന്നു നാഥൻ പറവകളെ","വയലിലെ താമര വളർത്തീടുന്നു","വിതയില്ല കൊയ്ത്തുമില്ല","സ്വർഗ്ഗനാഥൻ കരുതിടുന്നു - എന്നെ","സ്വർഗ്ഗനാഥൻ കരുതിടുന്നു"]},{"number":2,"lines":["നാളെയ്ക്കായി എന്തിന്നു ഞാൻ","വ്യാകുലനായി കലങ്ങീടുന്നു","എനിക്കായി കരുതിടുന്നു","വേണ്ടതെല്ലാം നാഥനവൻ - എന്നും","വേണ്ടതെല്ലാം നാഥനവൻ"]},{"number":3,"lines":["ശത്രുസൈന്യം ആഞ്ഞടിച്ചാൽ","ഭീതിവേണ്ടെനിക്കൊരുനാളും","കൂടെയുണ്ട് അധിപനവൻ","വീരനാമെൻ ദൈവമവൻ - എത്ര","വീരനാമെൻ ദൈവമവൻ"]}]}