{"number":1188,"writer":"IM","starts":"refrain","refrain":["യേശു മഹോന്നതനേ! ദിനവും","കൃപ ചൊരിഞ്ഞിടണമേ","കൂരിരുളിൻ നടുവിൽ നീ വഴികാട്ടിടണേ"],"verses":[{"number":1,"lines":[" പ്രതികൂലമേറുമീ മരുവാസമെന്നും","അനുകൂലമാക്കുമവൻ","ബലഹീനനായിടിലും എന്നും","ബലം തരും നാഥനവൻ"]},{"number":2,"lines":["ഉറ്റവരേവരും മാറിടുമെങ്കിലും","ഉടയവനേശുവുണ്ട്","നിന്ദിതനായിടിലും പാരിൽ","നിൻകൃപമതിയെനിക്ക്"]},{"number":3,"lines":["മാറാത്ത മാറയാണിന്നിവിടം","മാറുന്ന സ്നേഹിതരും","മാറ്റമില്ലാത്തവനായി നിത്യം","മനുവേലൻ കൂടെയുണ്ട്"]},{"number":4,"lines":["എന്നു നീ വന്നിടുമെൻ നാഥനേ!","എന്നാധിയകറ്റിടുവാൻ","നിന്നോടു ചേർന്നിടുവാൻ കാന്താ!","എന്നുളളം വാഞ്ഛിക്കുന്നു"]}]}