{"number":616,"writer":"CK","starts":"verse-1","refrain":["ഹല്ലേലുയ്യാ ഹല്ലേലുയ്യാ","ഹല്ലേലുയ്യാ ഏറ്റുപാടാം"],"verses":[{"number":1,"lines":["വിശ്വാസത്തോണിയിൽ","അക്കരെക്ക് പോകും നാം","ഹല്ലേലുയ്യാ എന്നും പാടാം"]},{"number":2,"lines":["അല്ലൽ പരന്നാലും","അലമാല വന്നാലും","ഉല്ലാസത്തോടെന്നും പാടാം"]},{"number":3,"lines":["കാറ്റങ്ങടിക്കുമ്പോൾ","ഊറ്റമായലറുമ്പോൾ","കൂട്ടിനായുണ്ടേശു നാഥൻ"]},{"number":4,"lines":["തീരത്തണയുവാൻ","തീരാമോദം പൂകുവാൻ","തീരെയില്ല നാളുകളിനി"]},{"number":5,"lines":["അന്ത്യം വരെയെന്നും","ചുക്കാൻ പിടിക്കുവാൻ","അമരത്തെന്നേശുവുണ്ട്"]}]}